E1608/E1608.py
E1608/__init__.py
e1608-0.1.3.dist-info/METADATA
e1608-0.1.3.dist-info/WHEEL
e1608-0.1.3.dist-info/licenses/LICENSE
e1608-0.1.3.dist-info/RECORD
