Metadata-Version: 2.3
Name: E1608
Version: 0.1.3
Summary: Python API for E1608 devices used by the TUCAN collaboration.
Project-URL: Homepage, https://github.com/mlavvaf/MCCDAQ
Project-URL: Bug Tracker, https://github.com/mlavvaf/MCCDAQ/issues
Author-email: Maedeh Lavvaf <mdhlvf@gmail.com>
License: MIT License
License-File: LICENSE
Classifier: License :: OSI Approved :: MIT License
Classifier: Operating System :: POSIX :: Linux
Classifier: Programming Language :: Python :: 3
Classifier: Programming Language :: Python :: 3.10
Requires-Python: >=3.7
Requires-Dist: matplotlib
Requires-Dist: mcculw
Requires-Dist: numpy
Requires-Dist: pandas
Requires-Dist: scipy
